README.txt
setup.py
django_madcap_flare.egg-info/PKG-INFO
django_madcap_flare.egg-info/SOURCES.txt
django_madcap_flare.egg-info/dependency_links.txt
django_madcap_flare.egg-info/requires.txt
django_madcap_flare.egg-info/top_level.txt
madcap_flare/__init__.py
madcap_flare/admin.py
madcap_flare/apps.py
madcap_flare/models.py
madcap_flare/tests.py
madcap_flare/views.py
madcap_flare/management/__init__.py
madcap_flare/management/commands/__init__.py
madcap_flare/management/commands/get_help_mapping.py
madcap_flare/migrations/__init__.py
madcap_flare/templatetags/__init__.py
madcap_flare/templatetags/madcap_flare_tags.py