Metadata-Version: 1.1
Name: django-madcap-flare
Version: 0.0.3
Summary: Integrate Madcap Flare docs into your Django project
Home-page: https://github.com/mypebble/django-madcap-flare
Author: Pebble
Author-email: scott.walton@mypebble.co.uk
License: MIT
Keywords: django madcap flare web development
Platform: UNKNOWN
Classifier: Development Status :: 3 - Alpha
Classifier: Intended Audience :: Developers
Classifier: Topic :: Software Development :: Build Tools
Classifier: License :: OSI Approved :: MIT License
Classifier: Programming Language :: Python :: 2
Classifier: Programming Language :: Python :: 2.7
Classifier: Programming Language :: Python :: 3
Classifier: Programming Language :: Python :: 3.3
Classifier: Programming Language :: Python :: 3.4
Classifier: Programming Language :: Python :: 3.5
